indiepitcher/__init__.py
indiepitcher/async_client.py
indiepitcher/client.py
indiepitcher/models.py
indiepitcher/py.typed
indiepitcher-0.1.0.dist-info/METADATA
indiepitcher-0.1.0.dist-info/WHEEL
indiepitcher-0.1.0.dist-info/RECORD
