Metadata-Version: 2.4
Name: indiepitcher
Version: 0.1.0
Summary: Python SDK for IndiePitcher
Project-URL: Homepage, https://github.com/IndiePitcher/indiepitcher-python
Project-URL: Documentation, https://docs.indiepitcher.com
Project-URL: Issues, https://github.com/IndiePitcher/indiepitcher-python/issues
Author-email: IndiePitcher <petr@indiepitcher.com>
License: MIT
Keywords: api,email,emails,marketing,newsletter,sdk
Classifier: Development Status :: 4 - Beta
Classifier: Intended Audience :: Developers
Classifier: License :: OSI Approved :: MIT License
Classifier: Programming Language :: Python :: 3
Classifier: Programming Language :: Python :: 3.9
Classifier: Programming Language :: Python :: 3.10
Classifier: Programming Language :: Python :: 3.11
Classifier: Programming Language :: Python :: 3.12
Classifier: Topic :: Communications :: Email
Classifier: Topic :: Software Development :: Libraries
Requires-Python: >=3.9
Requires-Dist: httpx>=0.28.1
Requires-Dist: pydantic>=2.11.2
